vidtoolz_add_text/__init__.py
vidtoolz_add_text/add_text.py
vidtoolz_add_text-0.4.1.dist-info/licenses/LICENSE
vidtoolz_add_text-0.4.1.dist-info/METADATA
vidtoolz_add_text-0.4.1.dist-info/WHEEL
vidtoolz_add_text-0.4.1.dist-info/entry_points.txt
vidtoolz_add_text-0.4.1.dist-info/top_level.txt
vidtoolz_add_text-0.4.1.dist-info/RECORD
