Metadata-Version: 2.4
Name: vidtoolz-add-text
Version: 0.4.1
Summary: Add text to a video file
Author: Sukhbinder Singh
License: Apache-2.0
Project-URL: Homepage, https://github.com/sukhbinder/vidtoolz-add-text
Project-URL: Changelog, https://github.com/sukhbinder/vidtoolz-add-text/releases
Project-URL: Issues, https://github.com/sukhbinder/vidtoolz-add-text/issues
Project-URL: CI, https://github.com/sukhbinder/vidtoolz-add-text/actions
Classifier: License :: OSI Approved :: Apache Software License
License-File: LICENSE
Requires-Dist: vidtoolz
Provides-Extra: test
Requires-Dist: pytest; extra == "test"
Dynamic: license-file
